gemi/__init__.py
gemi/document.py
gemi/enums.py
gemi/error.py
gemi/logger.py
gemi/message.py
gemi/misc.py
gemi/py.typed
gemi/client/__init__.py
gemi/client/__main__.py
gemi/client/cli.py
gemi/server/__init__.py
gemi/server/__main__.py
gemi/server/cli.py
gemi/server/router.py
gemi/server/server.py
gemi_python-0.1.4.dist-info/LICENSE.md
gemi_python-0.1.4.dist-info/METADATA
gemi_python-0.1.4.dist-info/WHEEL
gemi_python-0.1.4.dist-info/entry_points.txt
gemi_python-0.1.4.dist-info/top_level.txt
gemi_python-0.1.4.dist-info/RECORD
