Metadata-Version: 2.1
Name: gemi-python
Version: 0.1.4
Summary: Utilities for the Gemini protocol
Author-email: Zoey Mae <admin@barkshark.xyz>
License: CNPL 7+
Project-URL: Homepage, https://git.barkshark.xyz/barkshark/gemi
Project-URL: Bug Tracker, https://git.barkshark.xyz/barkshark/gemi/issues
Project-URL: Documentation, https://docs.barkshark.xyz/gemi
Project-URL: Source Code, https://git.barkshark.xyz/barkshark/gemi
Keywords: gemini,gemtext
Platform: any
Classifier: Development Status :: 4 - Beta
Classifier: Environment :: Console
Classifier: Intended Audience :: Developers
Classifier: Intended Audience :: End Users/Desktop
Classifier: License :: Other/Proprietary License
Classifier: Operating System :: OS Independent
Classifier: Programming Language :: Python
Classifier: Programming Language :: Python :: 3.10
Classifier: Programming Language :: Python :: 3.11
Classifier: Programming Language :: Python :: 3.12
Classifier: Topic :: Internet
Classifier: Topic :: Software Development :: Libraries :: Python Modules
Classifier: Typing :: Typed
Requires-Python: >=3.10
License-File: LICENSE.md
Requires-Dist: barkshark-lib <0.3.0,>=0.2.0
Requires-Dist: platformdirs ==4.2.0
Requires-Dist: pyopenssl ==24.1.0
Provides-Extra: dev
Requires-Dist: flake8 ==6.1.0 ; extra == 'dev'
Requires-Dist: mypy ==1.9.0 ; extra == 'dev'
Requires-Dist: pyinstaller ==6.5.0 ; extra == 'dev'
Requires-Dist: types-pyOpenSSL ==24.0.0.20240417 ; extra == 'dev'
Requires-Dist: typing-extensions ==4.12.2 ; (python_version < "3.11") and extra == 'dev'
Provides-Extra: docs
Requires-Dist: furo ==2024.1.29 ; extra == 'docs'
Requires-Dist: sphinx ==7.2.6 ; extra == 'docs'
Requires-Dist: sphinx-external-toc ==1.0.1 ; extra == 'docs'
